nitor_devel_backend/cli.py
nitor_devel_backend-0.1.26.dist-info/METADATA
nitor_devel_backend-0.1.26.dist-info/WHEEL
nitor_devel_backend-0.1.26.dist-info/entry_points.txt
nitor_devel_backend-0.1.26.dist-info/top_level.txt
nitor_devel_backend-0.1.26.dist-info/RECORD
