Metadata-Version: 2.1
Name: nitor-devel-backend
Version: 0.1.26
Summary: Tool for running a local proxy in docker to unify a local development backend and live Nitor API sources from dev or prod
Home-page: http://github.com/NitorCreations/nitor-devel-backend
Author: Pasi Niemi
Author-email: pasi.niemi@nitor.com
License: Apache 2.0
Download-URL: https://github.com/NitorCreations/nitor-devel-backend
Platform: UNKNOWN
Requires-Dist: nameless-deploy-tools (>=1.268)
